sysrsync/__init__.py
sysrsync/command_maker.py
sysrsync/exceptions.py
sysrsync/helpers/__init__.py
sysrsync/helpers/directories.py
sysrsync/helpers/iterators.py
sysrsync/helpers/rsync.py
sysrsync/runner.py
sysrsync-1.1.1.dist-info/LICENSE
sysrsync-1.1.1.dist-info/METADATA
sysrsync-1.1.1.dist-info/WHEEL
sysrsync-1.1.1.dist-info/RECORD
