Metadata-Version: 2.1
Name: sysrsync
Version: 1.1.1
Summary: Simple and safe python wrapper for calling system rsync
Home-page: https://github.com/gchamon/sysrsync
Author: Gabriel Chamon
Author-email: gchamon@live.com
Requires-Python: >=3.6,<4.0
Classifier: Programming Language :: Python :: 3
Classifier: Programming Language :: Python :: 3.6
Classifier: Programming Language :: Python :: 3.7
Classifier: Programming Language :: Python :: 3.8
Classifier: Programming Language :: Python :: 3.9
Classifier: Programming Language :: Python :: 3.10
Classifier: Programming Language :: Python :: 3.11
Requires-Dist: toml (>=0.10.0,<0.11.0)
